whoiser/Controller.py
whoiser/__init__.py
whoiser/__main__.py
whoiser-1.0.0.dist-info/LICENSE.md
whoiser-1.0.0.dist-info/METADATA
whoiser-1.0.0.dist-info/WHEEL
whoiser-1.0.0.dist-info/entry_points.txt
whoiser-1.0.0.dist-info/top_level.txt
whoiser-1.0.0.dist-info/RECORD
