Metadata-Version: 2.1
Name: whoiser
Version: 1.0.0
Summary: whois information for given IP addresses
Home-page: https://github.com/5f0ne/whoiser
Author: 5f0
License: MIT
Classifier: Operating System :: OS Independent 
Classifier: Programming Language :: Python :: 3 
Classifier: License :: OSI Approved :: MIT License 
License-File: LICENSE.md
Requires-Dist: ipwhois
